wrtn/__init__.py
wrtn/charmaker.py
wrtn/chat.py
wrtn/feed.py
wrtn/user.py
wrtn/variable.py
wrtn/wrtn.py
wrtn/exam/char_maker_test.py
wrtn/exam/chat_test.py
wrtn/exam/feed_test.py
wrtn/exam/user_info_test.py
wrtn-1.2.2.dist-info/LICENSE
wrtn-1.2.2.dist-info/METADATA
wrtn-1.2.2.dist-info/WHEEL
wrtn-1.2.2.dist-info/top_level.txt
wrtn-1.2.2.dist-info/RECORD
