Metadata-Version: 2.1
Name: wrtn
Version: 1.2.2
Summary: unoffical wrtn api
Home-page: https://github.com/sickwrtn/unoffical_wrtn_api
Author: sickwrtn
Author-email: sillo154265@gmail.com
License: MIT
Classifier: Development Status :: 4 - Beta
Classifier: Intended Audience :: Developers
Classifier: Programming Language :: Python :: 3
Classifier: Operating System :: OS Independent
Classifier: License :: OSI Approved :: MIT License
Requires-Python: >=3.7
License-File: LICENSE
Requires-Dist: requests==2.32.3
Requires-Dist: setuptools==75.6.0
